Workbook

Sheet Expenses
A1: Timestamp | B1: Date | C1: Category | D1: Subcategory | E1: Description | F1: Merchant/Store | G1: Amount | H1: Payment Method | I1: Meal Type | J1: Notes
A2: 2026-01-17T21:03:00 | B2: 2026-01-17 | C2: Subscriptions | D2: Streaming | E2: Monthly subscription | F2: Netflix | G2: 15.98 | H2: Credit Card
A3: 2026-01-13T20:23:00 | B3: 2026-01-13 | C3: Entertainment | D3: Movies | E3: Movie ticket - Avatar 3 | F3: GV Cinema | G3: 13.94 | H3: Credit Card
A4: 2026-01-12T22:37:00 | B4: 2026-01-12 | C4: Other | E4: Gift for friend | F4: Various | G4: 75.71 | H4: Cash
A5: 2026-01-08T12:35:00 | B5: 2026-01-08 | C5: Food & Dining | D5: Restaurants | E5: Lunch - Chicken Rice | F5: Tian Tian Hawker | G5: 5.5 | H5: Cash | I5: Lunch
A6: 2026-01-08T08:10:00 | B6: 2026-01-08 | C6: Transportation | D6: Gas/Fuel | E6: Full tank | F6: Shell | G6: 65 | H6: Credit Card
A7: 2026-01-07T19:05:00 | B7: 2026-01-07 | C7: Food & Dining | D7: Groceries | E7: Weekly groceries - vegetables and meat | F7: FairPrice | G7: 48.3 | H7: Debit Card
A8: 2026-01-07T09:20:00 | B8: 2026-01-07 | C8: Food & Dining | D8: Coffee/Snacks | E8: Iced Latte | F8: Starbucks | G8: 7.2 | H8: Credit Card | I8: Snack
A9: 2026-01-06T20:30:00 | B9: 2026-01-06 | C9: Shopping | D9: Clothing | E9: Running shoes | F9: Nike Store | G9: 129 | H9: Credit Card | J9: Birthday gift to myself
A10: 2026-01-06T19:45:00 | B10: 2026-01-06 | C10: Food & Dining | D10: Delivery | E10: Dinner - Pizza | F10: Dominos | G10: 25.9 | H10: Credit Card | I10: Dinner | J10: Family dinner
A11: 2026-01-06T14:52:00 | B11: 2026-01-06 | C11: Housing & Utilities | D11: Internet | E11: Monthly broadband | F11: Singtel | G11: 58.15 | H11: Credit Card
A12: 2026-01-05T22:15:00 | B12: 2026-01-05 | C12: Food & Dining | D12: Restaurants | E12: Lunch - Chicken Rice | F12: Tian Tian Hawker | G12: 7.19 | H12: Cash | I12: Lunch | J12: Family event
A13: 2026-01-05T21:10:00 | B13: 2026-01-05 | C13: Entertainment | D13: Movies | E13: Movie ticket - Avatar 3 | F13: GV Cinema | G13: 14.5 | H13: Credit Card
A14: 2026-01-05T08:00:00 | B14: 2026-01-05 | C14: Subscriptions | D14: Streaming | E14: Monthly subscription | F14: Netflix | G14: 15.98 | H14: Credit Card
A15: 2025-12-30T07:59:00 | B15: 2025-12-30 | C15: Work/Business | D15: Supplies | E15: Office supplies | F15: Office Depot | G15: 38.22 | H15: Credit Card
A16: 2025-12-28T22:08:00 | B16: 2025-12-28 | C16: Health | D16: Medical | E16: GP consultation | F16: Raffles Medical | G16: 53.76 | H16: Credit Card
A17: 2025-12-28T19:36:00 | B17: 2025-12-28 | C17: Housing & Utilities | D17: Phone | E17: Mobile plan | F17: StarHub | G17: 39.29 | H17: Credit Card
A18: 2025-12-25T11:04:00 | B18: 2025-12-25 | C18: Work/Business | D18: Supplies | E18: Office supplies | F18: Office Depot | G18: 37.47 | H18: Credit Card | J18: Work expense
A19: 2025-12-21T08:20:00 | B19: 2025-12-21 | C19: Shopping | D19: Electronics | E19: Phone charger | F19: Apple Store | G19: 47.42 | H19: Credit Card | J19: Work expense
A20: 2025-12-20T13:34:00 | B20: 2025-12-20 | C20: Education | D20: Courses | E20: Online course | F20: Udemy | G20: 25.75 | H20: Credit Card
A21: 2025-12-14T19:43:00 | B21: 2025-12-14 | C21: Health | D21: Medical | E21: GP consultation | F21: Raffles Medical | G21: 49.26 | H21: Credit Card
A22: 2025-12-09T22:16:00 | B22: 2025-12-09 | C22: Entertainment | D22: Movies | E22: Movie ticket - Latest blockbuster | F22: Shaw Theatres | G22: 13.00 | H22: E-Wallet
A23: 2025-11-29T11:24:00 | B23: 2025-11-29 | C23: Education | D23: Supplies | E23: Notebook and pens | F23: Popular Bookstore | G23: 20.63 | H23: Debit Card | J23: Sale discount
A24: 2025-11-27T09:18:00 | B24: 2025-11-27 | C24: Shopping | D24: Personal Care | E24: Skincare products | F24: Watsons | G24: 28.65 | H24: Credit Card
A25: 2025-11-26T15:15:00 | B25: 2025-11-26 | C25: Food & Dining | D25: Groceries | E25: Meat and seafood | F25: Cold Storage | G25: 66.98 | H25: Credit Card
A26: 2025-11-24T22:51:00 | B26: 2025-11-24 | C26: Transportation | D26: Ride Share | E26: Grab to office | F26: Grab | G26: 12.60 | H26: E-Wallet
A27: 2025-11-19T09:30:00 | B27: 2025-11-19 | C27: Transportation | D27: Parking | E27: Shopping mall parking | F27: Vivocity | G27: 6.93 | H27: Cash
A28: 2025-11-18T08:03:00 | B28: 2025-11-18 | C28: Transportation | D28: Parking | E28: Shopping mall parking | F28: Vivocity | G28: 3.74 | H28: E-Wallet
A29: 2025-11-17T14:52:00 | B29: 2025-11-17 | C29: Food & Dining | D29: Restaurants | E29: Breakfast - Kaya Toast Set | F29: Ya Kun Kaya Toast | G29: 6.88 | H29: Cash | I29: Breakfast
A30: 2025-11-12T14:32:00 | B30: 2025-11-12 | C30: Housing & Utilities | D30: Internet | E30: Monthly broadband | F30: Singtel | G30: 55.39 | H30: Credit Card
A31: 2025-11-10T16:35:00 | B31: 2025-11-10 | C31: Subscriptions | D31: Streaming | E31: Monthly subscription | F31: Spotify | G31: 9.99 | H31: Credit Card
A32: 2025-11-01T09:30:00 | B32: 2025-11-01 | C32: Other | E32: Gift for friend | F32: Various | G32: 76.50 | H32: Cash

Sheet Summary
A1: Expense Summary
A3: Total Expenses: | B3: =SUM(Expenses!G:G)
A4: This Month: | B4: =SUMIFS(Expenses!G:G,Expenses!B:B,">="&DATE(YEAR(TODAY()),MONTH(TODAY()),1))
A5: Transaction Count: | B5: =COUNTA(Expenses!A2:A)
A6: Average Transaction: | B6: =AVERAGE(Expenses!G:G)
A10: Category Breakdown
A11: Category | B11: Amount | C11: %
A12: Food & Dining | B12: =SUMIF(Expenses!C:C,A12,Expenses!G:G) | C12: =IF(B$3=0,0,B12/B$3)
A13: Transportation | B13: =SUMIF(Expenses!C:C,A13,Expenses!G:G) | C13: =IF(B$3=0,0,B13/B$3)
A14: Housing & Utilities | B14: =SUMIF(Expenses!C:C,A14,Expenses!G:G) | C14: =IF(B$3=0,0,B14/B$3)
A15: Subscriptions | B15: =SUMIF(Expenses!C:C,A15,Expenses!G:G) | C15: =IF(B$3=0,0,B15/B$3)
A16: Shopping | B16: =SUMIF(Expenses!C:C,A16,Expenses!G:G) | C16: =IF(B$3=0,0,B16/B$3)
A17: Health | B17: =SUMIF(Expenses!C:C,A17,Expenses!G:G) | C17: =IF(B$3=0,0,B17/B$3)
A18: Entertainment | B18: =SUMIF(Expenses!C:C,A18,Expenses!G:G) | C18: =IF(B$3=0,0,B18/B$3)
A19: Education | B19: =SUMIF(Expenses!C:C,A19,Expenses!G:G) | C19: =IF(B$3=0,0,B19/B$3)
A20: Work/Business | B20: =SUMIF(Expenses!C:C,A20,Expenses!G:G) | C20: =IF(B$3=0,0,B20/B$3)
A21: Other | B21: =SUMIF(Expenses!C:C,A21,Expenses!G:G) | C21: =IF(B$3=0,0,B21/B$3)

Sheet Reference
A1: Expense Tracker Reference
A2: Use this sheet as a reference for data entry guidelines
A4: Approved Categories
A5: Food & Dining
A6: Transportation
A7: Housing & Utilities
A8: Subscriptions
A9: Shopping
A10: Health
A11: Entertainment
A12: Education
A13: Work/Business
... A16: Subcategory Reference
A17: Category | B17: Recommended Subcategories
A18: Food & Dining | B18: Groceries, Restaurants, Coffee/Snacks, Delivery
A19: Transportation | B19: Gas/Fuel, Public Transit, Parking, Ride Share, Maintenance
A20: Housing & Utilities | B20: Rent, Electricity, Water, Internet, Phone
A21: Subscriptions | B21: Streaming, Software, Memberships
A22: Shopping | B22: Clothing, Electronics, Home, Personal Care
A23: Health | B23: Medical, Pharmacy, Fitness, Insurance
A24: Entertainment | B24: Movies, Games, Events, Hobbies
A25: Education | B25: Courses, Books, Supplies
A26: Work/Business | B26: Supplies, Travel, Equipment
A28: Payment Methods
A29: Cash
A30: Credit Card
A31: Debit Card
A32: E-Wallet
A33: Bank Transfer
A35: Meal Types
A36: (Only for Food & Dining entries)
A37: Breakfast
A38: Lunch
A39: Dinner
A40: Snack
